langgraph/config.py
langgraph/constants.py
langgraph/errors.py
langgraph/py.typed
langgraph/types.py
langgraph/version.py
langgraph/_api/__init__.py
langgraph/_api/deprecation.py
langgraph/channels/__init__.py
langgraph/channels/any_value.py
langgraph/channels/base.py
langgraph/channels/binop.py
langgraph/channels/context.py
langgraph/channels/dynamic_barrier_value.py
langgraph/channels/ephemeral_value.py
langgraph/channels/last_value.py
langgraph/channels/named_barrier_value.py
langgraph/channels/py.typed
langgraph/channels/topic.py
langgraph/channels/untracked_value.py
langgraph/checkpoint/base/__init__.py
langgraph/checkpoint/base/id.py
langgraph/checkpoint/base/py.typed
langgraph/checkpoint/memory/__init__.py
langgraph/checkpoint/memory/py.typed
langgraph/checkpoint/serde/__init__.py
langgraph/checkpoint/serde/base.py
langgraph/checkpoint/serde/encrypted.py
langgraph/checkpoint/serde/jsonplus.py
langgraph/checkpoint/serde/py.typed
langgraph/checkpoint/serde/types.py
langgraph/func/__init__.py
langgraph/func/py.typed
langgraph/graph/__init__.py
langgraph/graph/branch.py
langgraph/graph/graph.py
langgraph/graph/message.py
langgraph/graph/py.typed
langgraph/graph/schema_utils.py
langgraph/graph/state.py
langgraph/managed/__init__.py
langgraph/managed/base.py
langgraph/managed/context.py
langgraph/managed/is_last_step.py
langgraph/managed/py.typed
langgraph/managed/shared_value.py
langgraph/prebuilt/__init__.py
langgraph/prebuilt/chat_agent_executor.py
langgraph/prebuilt/interrupt.py
langgraph/prebuilt/py.typed
langgraph/prebuilt/tool_node.py
langgraph/prebuilt/tool_validator.py
langgraph/pregel/__init__.py
langgraph/pregel/algo.py
langgraph/pregel/call.py
langgraph/pregel/debug.py
langgraph/pregel/executor.py
langgraph/pregel/io.py
langgraph/pregel/log.py
langgraph/pregel/loop.py
langgraph/pregel/manager.py
langgraph/pregel/messages.py
langgraph/pregel/protocol.py
langgraph/pregel/py.typed
langgraph/pregel/read.py
langgraph/pregel/remote.py
langgraph_aipy-0.3.18.dist-info/METADATA
langgraph_aipy-0.3.18.dist-info/WHEEL
langgraph_aipy-0.3.18.dist-info/top_level.txt
langgraph_aipy-0.3.18.dist-info/RECORD
