Metadata-Version: 2.4
Name: langgraph-aipy
Version: 0.3.18
Summary: Building stateful, multi-actor applications with LLMs
Author-email: The QPYPI Team <qpypi@qpython.org>
License: MIT AND (Apache-2.0 OR BSD-2-Clause)
Project-URL: Homepage, https://qpypi.qpython.org/project/langgraph-aipy/
Classifier: Intended Audience :: Developers
Classifier: Intended Audience :: Education
Classifier: Intended Audience :: Information Technology
Classifier: Intended Audience :: End Users/Desktop
Classifier: License :: OSI Approved :: Apache Software License
Classifier: Operating System :: Android
Classifier: Programming Language :: Python
Classifier: Programming Language :: Python :: 3.12
Classifier: Topic :: Software Development
Requires-Python: ==3.12.*
Requires-Dist: httpx
Requires-Dist: orjson-qpython
Requires-Dist: msgpack-qpython
Requires-Dist: langchain-core-aipy
